{"timestamp": 1746372129.151321, "coins": [{"name": "Bitcoin", "price": 84729.89, "tp": 5.0, "sl": 3.0, "has_trade": false, "status": "-", "entry": 0.0, "trades": 0, "gain": 0, "best": 0, "worst": 0, "ema15": 84683.4479, "ema1h": 84876.5047, "mod": 1.889999999999418, "vol_now": 2.68886, "vol_avg": 6.633156000000001, "score": 0.2, "signal": "Schwach"}, {"name": "Ethereum", "price": 1621.62, "tp": 4.0, "sl": 2.5, "has_trade": false, "status": "-", "entry": 0.0, "trades": 0, "gain": 0, "best": 0, "worst": 0, "ema15": 1622.1431, "ema1h": 1623.7232, "mod": 1.6199999999998909, "vol_now": 54.8602, "vol_avg": 142.82594, "score": 0.05, "signal": "Schwach"}, {"name": "Solana", "price": 130.11, "tp": 6.0, "sl": 3.5, "has_trade": false, "status": "-", "entry": 0.0, "trades": 0, "gain": 0, "best": 0, "worst": 0, "ema15": 129.3667, "ema1h": 129.5775, "mod": 4.110000000000014, "vol_now": 413.945, "vol_avg": 918.8759, "score": 0.35, "signal": "Schwach"}, {"name": "XRP", "price": 1.9472, "tp": 6.0, "sl": 3.0, "has_trade": false, "status": "-", "entry": 0.0, "trades": 0, "gain": 0, "best": 0, "worst": 0, "ema15": 1.9417, "ema1h": 1.9446, "mod": 1.9472, "vol_now": 40482.1, "vol_avg": 49125.08, "score": 0.35, "signal": "Schwach"}, {"name": "Polygon", "price": 0.3444, "tp": 6.5, "sl": 3.2, "has_trade": false, "status": "-", "entry": 0.0, "trades": 0, "gain": 0, "best": 0, "worst": 0, "ema15": 0.3455, "ema1h": 0.344, "mod": 0.3444, "vol_now": 293.8, "vol_avg": 14542.12, "score": 0.24, "signal": "Schwach"}, {"name": "Cardano", "price": 0.6129, "tp": 5.5, "sl": 3.0, "has_trade": false, "status": "-", "entry": 0.0, "trades": 0, "gain": 0, "best": 0, "worst": 0, "ema15": 0.612, "ema1h": 0.6172, "mod": 0.6129, "vol_now": 23204.3, "vol_avg": 66088.62999999999, "score": 0.2, "signal": "Schwach"}, {"name": "Litecoin", "price": 76.76, "tp": 4.5, "sl": 2.8, "has_trade": false, "status": "-", "entry": 0.0, "trades": 0, "gain": 0, "best": 0, "worst": 0, "ema15": 76.4504, "ema1h": 76.5339, "mod": 4.760000000000005, "vol_now": 41.1, "vol_avg": 95.8894, "score": 0.35, "signal": "Schwach"}, {"name": "Dogecoin", "price": 0.15412, "tp": 7.0, "sl": 4.0, "has_trade": false, "status": "-", "entry": 0.0, "trades": 0, "gain": 0, "best": 0, "worst": 0, "ema15": 0.1542, "ema1h": 0.1552, "mod": 0.15412, "vol_now": 66736.0, "vol_avg": 214810.4, "score": 0.23, "signal": "Schwach"}, {"name": "Shiba Inu", "price": 1.141e-05, "tp": 8.0, "sl": 5.0, "has_trade": false, "status": "-", "entry": 0.0, "trades": 0, "gain": 0, "best": 0, "worst": 0, "ema15": 0.0, "ema1h": 0.0, "mod": 1.141e-05, "vol_now": 209279436.0, "vol_avg": 392461306.6, "score": 0.65, "signal": "Neutral"}, {"name": "Pepe", "price": 7.26e-06, "tp": 10.0, "sl": 6.0, "has_trade": false, "status": "-", "entry": 0.0, "trades": 0, "gain": 0, "best": 0, "worst": 0, "ema15": 0.0, "ema1h": 0.0, "mod": 7.26e-06, "vol_now": 201137272.0, "vol_avg": 1012297194.3, "score": 0.65, "signal": "Neutral"}, {"name": "Avalanche", "price": 17.74, "tp": 6.0, "sl": 3.0, "has_trade": false, "status": "-", "entry": 0.0, "trades": 0, "gain": 0, "best": 0, "worst": 0, "ema15": 17.7664, "ema1h": 17.9728, "mod": 3.7399999999999984, "vol_now": 188.34, "vol_avg": 194.077, "score": 0.05, "signal": "Schwach"}, {"name": "Chainlink", "price": 12.57, "tp": 5.5, "sl": 3.0, "has_trade": false, "status": "-", "entry": 0.0, "trades": 0, "gain": 0, "best": 0, "worst": 0, "ema15": 12.4993, "ema1h": 12.5573, "mod": 0.5700000000000003, "vol_now": 1107.96, "vol_avg": 1111.067, "score": 0.35, "signal": "Schwach"}, {"name": "Arbitrum", "price": 0.2805, "tp": 6.5, "sl": 3.5, "has_trade": false, "status": "-", "entry": 0.0, "trades": 0, "gain": 0, "best": 0, "worst": 0, "ema15": 0.2806, "ema1h": 0.2833, "mod": 0.2805, "vol_now": 3668.7, "vol_avg": 1831.9100000000003, "score": 0.44, "signal": "Schwach"}, {"name": "Aptos", "price": 4.556, "tp": 7.0, "sl": 3.0, "has_trade": false, "status": "-", "entry": 0.0, "trades": 0, "gain": 0, "best": 0, "worst": 0, "ema15": 4.5626, "ema1h": 4.5827, "mod": 4.556, "vol_now": 69.49, "vol_avg": 162.673, "score": 0.05, "signal": "Schwach"}, {"name": "Optimism", "price": 0.606, "tp": 6.0, "sl": 3.0, "has_trade": false, "status": "-", "entry": 0.0, "trades": 0, "gain": 0, "best": 0, "worst": 0, "ema15": 0.6045, "ema1h": 0.6049, "mod": 0.606, "vol_now": 0.0, "vol_avg": 5944.477, "score": 0.35, "signal": "Schwach"}, {"name": "Uniswap", "price": 4.856, "tp": 5.5, "sl": 3.0, "has_trade": false, "status": "-", "entry": 0.0, "trades": 0, "gain": 0, "best": 0, "worst": 0, "ema15": 4.856, "ema1h": 4.8186, "mod": 4.856, "vol_now": 0.0, "vol_avg": 111.822, "score": 0.2, "signal": "Schwach"}, {"name": "Cosmos", "price": 3.69, "tp": 6.0, "sl": 3.0, "has_trade": false, "status": "-", "entry": 0.0, "trades": 0, "gain": 0, "best": 0, "worst": 0, "ema15": 3.672, "ema1h": 3.7092, "mod": 3.69, "vol_now": 13.28, "vol_avg": 329.122, "score": 0.2, "signal": "Schwach"}, {"name": "Near", "price": 2.104, "tp": 6.5, "sl": 3.0, "has_trade": false, "status": "-", "entry": 0.0, "trades": 0, "gain": 0, "best": 0, "worst": 0, "ema15": 2.1125, "ema1h": 2.1353, "mod": 2.104, "vol_now": 194.7, "vol_avg": 678.2900000000001, "score": 0.05, "signal": "Schwach"}, {"name": "Internet Comp.", "price": 4.118, "tp": 7.0, "sl": 3.5, "has_trade": false, "status": "-", "entry": 0.0, "trades": 0, "gain": 0, "best": 0, "worst": 0, "ema15": 4.1246, "ema1h": 4.1527, "mod": 4.118, "vol_now": 92.29, "vol_avg": 849.0799999999999, "score": 0.05, "signal": "Schwach"}]}