{"timestamp": 1746414744.0785985, "coins": [{"name": "Bitcoin", "price": 83125.07, "tp": 5.0, "sl": 3.0, "has_trade": false, "status": "-", "entry": 0.0, "trades": 0, "gain": 0, "best": 0, "worst": 0, "ema15": 83528.8252, "ema1h": 84160.3017, "mod": 5.070000000006985, "vol_now": 0.53874, "vol_avg": 9.508569, "score": 0.05, "signal": "Schwach"}, {"name": "Ethereum", "price": 1586.32, "tp": 4.0, "sl": 2.5, "has_trade": false, "status": "-", "entry": 0.0, "trades": 0, "gain": 0, "best": 0, "worst": 0, "ema15": 1597.2648, "ema1h": 1611.0313, "mod": 6.319999999999936, "vol_now": 27.7018, "vol_avg": 269.71934999999996, "score": 0.05, "signal": "Schwach"}, {"name": "Solana", "price": 127.68, "tp": 6.0, "sl": 3.5, "has_trade": false, "status": "-", "entry": 0.0, "trades": 0, "gain": 0, "best": 0, "worst": 0, "ema15": 127.9351, "ema1h": 128.863, "mod": 7.680000000000007, "vol_now": 106.674, "vol_avg": 1109.3644, "score": 0.05, "signal": "Schwach"}, {"name": "XRP", "price": 1.9046, "tp": 6.0, "sl": 3.0, "has_trade": false, "status": "-", "entry": 0.0, "trades": 0, "gain": 0, "best": 0, "worst": 0, "ema15": 1.909, "ema1h": 1.9245, "mod": 1.9046, "vol_now": 4042.8, "vol_avg": 59784.7, "score": 0.05, "signal": "Schwach"}, {"name": "Polygon", "price": 0.3444, "tp": 6.5, "sl": 3.2, "has_trade": false, "status": "-", "entry": 0.0, "trades": 0, "gain": 0, "best": 0, "worst": 0, "ema15": 0.3455, "ema1h": 0.344, "mod": 0.3444, "vol_now": 293.8, "vol_avg": 14542.12, "score": 0.24, "signal": "Schwach"}, {"name": "Cardano", "price": 0.595, "tp": 5.5, "sl": 3.0, "has_trade": false, "status": "-", "entry": 0.0, "trades": 0, "gain": 0, "best": 0, "worst": 0, "ema15": 0.5984, "ema1h": 0.606, "mod": 0.595, "vol_now": 4474.8, "vol_avg": 75601.87, "score": 0.05, "signal": "Schwach"}, {"name": "Litecoin", "price": 75.92, "tp": 4.5, "sl": 2.8, "has_trade": false, "status": "-", "entry": 0.0, "trades": 0, "gain": 0, "best": 0, "worst": 0, "ema15": 75.7541, "ema1h": 76.158, "mod": 5.920000000000002, "vol_now": 61.722, "vol_avg": 245.8518, "score": 0.2, "signal": "Schwach"}, {"name": "Dogecoin", "price": 0.15076, "tp": 7.0, "sl": 4.0, "has_trade": false, "status": "-", "entry": 0.0, "trades": 0, "gain": 0, "best": 0, "worst": 0, "ema15": 0.1511, "ema1h": 0.1526, "mod": 0.15076, "vol_now": 74685.0, "vol_avg": 300353.9, "score": 0.24, "signal": "Schwach"}, {"name": "Shiba Inu", "price": 1.133e-05, "tp": 8.0, "sl": 5.0, "has_trade": false, "status": "-", "entry": 0.0, "trades": 0, "gain": 0, "best": 0, "worst": 0, "ema15": 0.0, "ema1h": 0.0, "mod": 1.133e-05, "vol_now": 51052214.0, "vol_avg": 447304213.8, "score": 0.65, "signal": "Neutral"}, {"name": "Pepe", "price": 7.25e-06, "tp": 10.0, "sl": 6.0, "has_trade": false, "status": "-", "entry": 0.0, "trades": 0, "gain": 0, "best": 0, "worst": 0, "ema15": 0.0, "ema1h": 0.0, "mod": 7.25e-06, "vol_now": 271565725.0, "vol_avg": 2210235250.5, "score": 0.65, "signal": "Neutral"}, {"name": "Avalanche", "price": 17.76, "tp": 6.0, "sl": 3.0, "has_trade": false, "status": "-", "entry": 0.0, "trades": 0, "gain": 0, "best": 0, "worst": 0, "ema15": 17.6959, "ema1h": 17.8063, "mod": 7.760000000000002, "vol_now": 29.37, "vol_avg": 159.473, "score": 0.2, "signal": "Schwach"}, {"name": "Chainlink", "price": 12.31, "tp": 5.5, "sl": 3.0, "has_trade": false, "status": "-", "entry": 0.0, "trades": 0, "gain": 0, "best": 0, "worst": 0, "ema15": 12.326, "ema1h": 12.4193, "mod": 2.3100000000000005, "vol_now": 47.44, "vol_avg": 946.673, "score": 0.05, "signal": "Schwach"}, {"name": "Arbitrum", "price": 0.278, "tp": 6.5, "sl": 3.5, "has_trade": false, "status": "-", "entry": 0.0, "trades": 0, "gain": 0, "best": 0, "worst": 0, "ema15": 0.2765, "ema1h": 0.2785, "mod": 0.278, "vol_now": 0.0, "vol_avg": 3663.04, "score": 0.29, "signal": "Schwach"}, {"name": "Aptos", "price": 4.551, "tp": 7.0, "sl": 3.0, "has_trade": false, "status": "-", "entry": 0.0, "trades": 0, "gain": 0, "best": 0, "worst": 0, "ema15": 4.5302, "ema1h": 4.5476, "mod": 4.551, "vol_now": 0.0, "vol_avg": 419.09900000000005, "score": 0.35, "signal": "Schwach"}, {"name": "Optimism", "price": 0.597, "tp": 6.0, "sl": 3.0, "has_trade": false, "status": "-", "entry": 0.0, "trades": 0, "gain": 0, "best": 0, "worst": 0, "ema15": 0.5912, "ema1h": 0.5941, "mod": 0.597, "vol_now": 1201.97, "vol_avg": 1412.599, "score": 0.35, "signal": "Schwach"}, {"name": "Uniswap", "price": 4.856, "tp": 5.5, "sl": 3.0, "has_trade": false, "status": "-", "entry": 0.0, "trades": 0, "gain": 0, "best": 0, "worst": 0, "ema15": 4.856, "ema1h": 4.8186, "mod": 4.856, "vol_now": 0.0, "vol_avg": 111.822, "score": 0.2, "signal": "Schwach"}, {"name": "Cosmos", "price": 3.671, "tp": 6.0, "sl": 3.0, "has_trade": false, "status": "-", "entry": 0.0, "trades": 0, "gain": 0, "best": 0, "worst": 0, "ema15": 3.634, "ema1h": 3.6587, "mod": 3.671, "vol_now": 153.94, "vol_avg": 174.12399999999997, "score": 0.35, "signal": "Schwach"}, {"name": "Near", "price": 2.082, "tp": 6.5, "sl": 3.0, "has_trade": false, "status": "-", "entry": 0.0, "trades": 0, "gain": 0, "best": 0, "worst": 0, "ema15": 2.0599, "ema1h": 2.0854, "mod": 2.082, "vol_now": 0.0, "vol_avg": 389.75, "score": 0.2, "signal": "Schwach"}, {"name": "Internet Comp.", "price": 4.085, "tp": 7.0, "sl": 3.5, "has_trade": false, "status": "-", "entry": 0.0, "trades": 0, "gain": 0, "best": 0, "worst": 0, "ema15": 4.0775, "ema1h": 4.1006, "mod": 4.085, "vol_now": 2175.25, "vol_avg": 268.341, "score": 0.5, "signal": "Neutral"}]}