{"timestamp": 1746258583.9196296, "coins": [{"name": "Bitcoin", "price": 85398.3, "tp": 5.0, "sl": 3.0, "has_trade": false, "status": "-", "entry": 0.0, "trades": 0, "gain": 0, "best": 0, "worst": 0, "ema15": 85422.7819, "ema1h": 85592.7283, "mod": 5.30000000000291, "vol_now": 4.31939, "vol_avg": 3.1593210000000003, "score": 0.16, "signal": "Schwach"}, {"name": "Ethereum", "price": 1619.84, "tp": 4.0, "sl": 2.5, "has_trade": false, "status": "-", "entry": 0.0, "trades": 0, "gain": 0, "best": 0, "worst": 0, "ema15": 1622.851, "ema1h": 1625.6915, "mod": 4.839999999999918, "vol_now": 144.1168, "vol_avg": 85.19064, "score": 0.26, "signal": "Schwach"}, {"name": "Solana", "price": 131.24, "tp": 6.0, "sl": 3.5, "has_trade": false, "status": "-", "entry": 0.0, "trades": 0, "gain": 0, "best": 0, "worst": 0, "ema15": 131.1226, "ema1h": 131.6224, "mod": 5.240000000000009, "vol_now": 346.006, "vol_avg": 505.1911, "score": 0.2, "signal": "Schwach"}, {"name": "XRP", "price": 1.9523, "tp": 6.0, "sl": 3.0, "has_trade": false, "status": "-", "entry": 0.0, "trades": 0, "gain": 0, "best": 0, "worst": 0, "ema15": 1.9564, "ema1h": 1.9574, "mod": 1.9523, "vol_now": 17152.7, "vol_avg": 24034.56, "score": 0.05, "signal": "Schwach"}, {"name": "Polygon", "price": 0.3444, "tp": 6.5, "sl": 3.2, "has_trade": false, "status": "-", "entry": 0.0, "trades": 0, "gain": 0, "best": 0, "worst": 0, "ema15": 0.3455, "ema1h": 0.344, "mod": 0.3444, "vol_now": 293.8, "vol_avg": 14542.12, "score": 0.24, "signal": "Schwach"}, {"name": "Cardano", "price": 0.6192, "tp": 5.5, "sl": 3.0, "has_trade": false, "status": "-", "entry": 0.0, "trades": 0, "gain": 0, "best": 0, "worst": 0, "ema15": 0.6184, "ema1h": 0.6198, "mod": 0.6192, "vol_now": 17053.7, "vol_avg": 28604.25, "score": 0.2, "signal": "Schwach"}, {"name": "Litecoin", "price": 76.94, "tp": 4.5, "sl": 2.8, "has_trade": false, "status": "-", "entry": 0.0, "trades": 0, "gain": 0, "best": 0, "worst": 0, "ema15": 77.256, "ema1h": 77.6917, "mod": 4.939999999999998, "vol_now": 103.412, "vol_avg": 125.3816, "score": 0.05, "signal": "Schwach"}, {"name": "Dogecoin", "price": 0.15855, "tp": 7.0, "sl": 4.0, "has_trade": false, "status": "-", "entry": 0.0, "trades": 0, "gain": 0, "best": 0, "worst": 0, "ema15": 0.1593, "ema1h": 0.1599, "mod": 0.15855, "vol_now": 249589.0, "vol_avg": 178189.6, "score": 0.35, "signal": "Schwach"}, {"name": "Shiba Inu", "price": 1.175e-05, "tp": 8.0, "sl": 5.0, "has_trade": false, "status": "-", "entry": 0.0, "trades": 0, "gain": 0, "best": 0, "worst": 0, "ema15": 0.0, "ema1h": 0.0, "mod": 1.175e-05, "vol_now": 213012588.0, "vol_avg": 214126140.2, "score": 0.65, "signal": "Neutral"}, {"name": "Pepe", "price": 7.53e-06, "tp": 10.0, "sl": 6.0, "has_trade": false, "status": "-", "entry": 0.0, "trades": 0, "gain": 0, "best": 0, "worst": 0, "ema15": 0.0, "ema1h": 0.0, "mod": 7.53e-06, "vol_now": 1290064284.0, "vol_avg": 13569198924.5, "score": 0.65, "signal": "Neutral"}]}